asf_metadata/__init__.py
asf_metadata/generate_iso_metadata.py
asf_metadata/generate_iso_template.py
asf_metadata/generate_project_metadata.py
asf_metadata/images/iso_metadata.png
asf_metadata/images/iso_metadata_structure.png
asf_metadata/images/namespaces_lut.png
asf_metadata/images/namespaces_url.png
asf_metadata/metadata/__init__.py
asf_metadata/metadata/asf_metadata.py
asf_metadata/metadata/sentinel_metadata.py
asf_metadata/metadata/util.py
asf_metadata/templates/dem/dem_copernicus_metadata.xlsx
asf_metadata/templates/dem/dem_trex_metadata.xlsx
asf_metadata/templates/projects/pcm_sentinel_metadata.xlsx
asf_metadata/templates/sentinel/sentinel_burst_metadata_umm.xlsx
asf_metadata/templates/sentinel/sentinel_gamma_rtc_metadata.xlsx
asf_metadata/templates/sentinel/sentinel_rtc_metadata.xlsx
asf_metadata-0.2.0.dist-info/LICENSE
asf_metadata-0.2.0.dist-info/METADATA
asf_metadata-0.2.0.dist-info/WHEEL
asf_metadata-0.2.0.dist-info/top_level.txt
asf_metadata-0.2.0.dist-info/RECORD
