Metadata-Version: 2.1
Name: asf-metadata
Version: 0.2.0
Summary: Python wrapper for ASF's metadata
Home-page: https://github.com/asfadmin/asf_metadata.git
Author: Alaska Satellite Facility Coop Team
Author-email: UAF-ASF-CD@alaska.edu
License: BSD
Project-URL: Documentation, https://github.com/asfadmin/asf_metadata
Classifier: Development Status :: 2 - Pre-Alpha
Classifier: License :: OSI Approved :: BSD License
Classifier: Operating System :: OS Independent
Classifier: Intended Audience :: Developers
Classifier: Intended Audience :: Science/Research
Classifier: Programming Language :: Python :: 3
Classifier: Programming Language :: Python :: 3 :: Only
Classifier: Programming Language :: Python :: 3.6
Classifier: Programming Language :: Python :: 3.7
Classifier: Programming Language :: Python :: 3.8
Classifier: Programming Language :: Python :: 3.9
Classifier: Topic :: Software Development
Classifier: Topic :: Scientific/Engineering :: Atmospheric Science
Classifier: Topic :: Scientific/Engineering :: GIS
Classifier: Topic :: Scientific/Engineering :: Hydrology
Classifier: Topic :: Utilities
Requires-Python: >=3.6
License-File: LICENSE
Requires-Dist: defusedxml
Requires-Dist: flatdict
Requires-Dist: numpy
Requires-Dist: scipy
Requires-Dist: openpyxl
Requires-Dist: pandas
Requires-Dist: geopandas
Requires-Dist: sqlalchemy
Requires-Dist: requests
Requires-Dist: remotezip
Requires-Dist: geoalchemy2
Requires-Dist: psycopg2
Requires-Dist: xmltodict
Provides-Extra: test
